{"mc":{"110130_r_7":{"frameRate":15,"frames":[{"y":-98,"res":"70000.png","x":-55},{"y":-101,"res":"70001.png","x":-60},{"y":-103,"res":"70002.png","x":-62},{"y":-101,"res":"70003.png","x":-60},{"y":-98,"res":"70004.png","x":-59},{"y":-100,"res":"70005.png","x":-60},{"y":-103,"res":"70006.png","x":-62},{"y":-101,"res":"70007.png","x":-60}]}},"res":{"70006.png":{"x":178,"y":104,"w":86,"h":115},"70004.png":{"x":85,"y":106,"w":89,"h":107},"70000.png":{"x":0,"y":0,"w":85,"h":109},"70001.png":{"x":85,"y":0,"w":93,"h":106},"70005.png":{"x":350,"y":0,"w":93,"h":112},"70007.png":{"x":0,"y":109,"w":84,"h":112},"70002.png":{"x":178,"y":0,"w":87,"h":104},"70003.png":{"x":265,"y":0,"w":85,"h":109}}}