{"mc":{"110100_a_5":{"frameRate":15,"frames":[{"y":-80,"res":"50000.png","x":-54},{"y":-79,"res":"50001.png","x":-54},{"y":-77,"res":"50002.png","x":-54},{"y":-84,"res":"50003.png","x":-54},{"y":-81,"res":"50004.png","x":-54},{"y":-81,"res":"50005.png","x":-54}]}},"res":{"50000.png":{"x":0,"y":0,"w":108,"h":118},"50004.png":{"x":216,"y":94,"w":108,"h":146},"50003.png":{"x":324,"y":0,"w":108,"h":101},"50005.png":{"x":108,"y":101,"w":108,"h":138},"50002.png":{"x":216,"y":0,"w":108,"h":94},"50001.png":{"x":108,"y":0,"w":108,"h":96}}}