{"mc":{"110130_r_4":{"frameRate":15,"frames":[{"y":-92,"res":"40000.png","x":-59},{"y":-95,"res":"40001.png","x":-47},{"y":-96,"res":"40002.png","x":-38},{"y":-95,"res":"40003.png","x":-37},{"y":-94,"res":"40004.png","x":-37},{"y":-97,"res":"40005.png","x":-37},{"y":-96,"res":"40006.png","x":-38},{"y":-95,"res":"40007.png","x":-47}]}},"res":{"40003.png":{"x":201,"y":0,"w":78,"h":109},"40000.png":{"x":0,"y":0,"w":108,"h":108},"40005.png":{"x":201,"y":109,"w":78,"h":111},"40001.png":{"x":108,"y":0,"w":93,"h":111},"40007.png":{"x":78,"y":217,"w":93,"h":104},"40004.png":{"x":279,"y":0,"w":78,"h":111},"40006.png":{"x":78,"y":111,"w":78,"h":106},"40002.png":{"x":0,"y":108,"w":78,"h":106}}}