{"res":{"30002.png":{"x":0,"y":1122,"w":880,"h":566},"30005.png":{"x":0,"y":0,"w":0,"h":0},"30004.png":{"x":0,"y":0,"w":0,"h":0},"30000.png":{"x":0,"y":0,"w":891,"h":570},"30003.png":{"x":0,"y":0,"w":0,"h":0},"30001.png":{"x":0,"y":570,"w":882,"h":552}},"mc":{"210130_r_3":{"frames":[{"res":"30000.png","y":-495,"x":-669},{"res":"30001.png","y":-511,"x":-659},{"res":"30002.png","y":-500,"x":-656},{"res":"30003.png","y":-453,"x":-675},{"res":"30004.png","y":-463,"x":-680},{"res":"30005.png","y":-473,"x":-670}],"frameRate":15}}}