{"res":{"60003.png":{"x":0,"y":0,"w":0,"h":0},"60001.png":{"x":0,"y":659,"w":525,"h":657},"60005.png":{"x":0,"y":0,"w":0,"h":0},"60000.png":{"x":0,"y":0,"w":553,"h":659},"60002.png":{"x":0,"y":1316,"w":588,"h":662},"60004.png":{"x":0,"y":0,"w":0,"h":0}},"mc":{"210260_c_6":{"frames":[{"res":"60000.png","y":-560,"x":-174},{"res":"60001.png","y":-558,"x":-174},{"res":"60002.png","y":-563,"x":-174},{"res":"60003.png","y":-562,"x":-194},{"res":"60004.png","y":-499,"x":-222},{"res":"60005.png","y":-480,"x":-228}],"frameRate":15}}}