{"res":{"70004.png":{"x":0,"y":0,"w":0,"h":0},"70003.png":{"x":0,"y":0,"w":0,"h":0},"70002.png":{"x":0,"y":1258,"w":755,"h":523},"70000.png":{"x":0,"y":0,"w":744,"h":651},"70001.png":{"x":0,"y":651,"w":742,"h":607},"70005.png":{"x":0,"y":0,"w":0,"h":0}},"mc":{"210260_r_7":{"frames":[{"res":"70000.png","y":-578,"x":-227},{"res":"70001.png","y":-544,"x":-229},{"res":"70002.png","y":-453,"x":-229},{"res":"70003.png","y":-454,"x":-229},{"res":"70004.png","y":-550,"x":-227},{"res":"70005.png","y":-608,"x":-227}],"frameRate":15}}}