{"res":{"60000":{"x":0,"y":0,"w":47,"h":94},"60001":{"x":47,"y":0,"w":51,"h":96},"60002":{"x":98,"y":0,"w":50,"h":97},"60003":{"x":0,"y":96,"w":50,"h":95},"60004":{"x":0,"y":191,"w":57,"h":95},"60005":{"x":148,"y":0,"w":62,"h":96},"60006":{"x":50,"y":97,"w":70,"h":90}},"mc":{"70101_c_6":{"frameRate":15,"frames":[{"y":-130,"res":"60000","x":-5},{"y":-132,"res":"60001","x":-6},{"y":-133,"res":"60002","x":-2},{"y":-130,"res":"60003","x":1},{"y":-128,"res":"60004","x":0},{"y":-129,"res":"60005","x":-1},{"y":-131,"res":"60006","x":-12}]}}}