{"res":{"80000":{"x":0,"y":0,"w":238,"h":162},"80001":{"x":238,"y":0,"w":201,"h":163},"80002":{"x":0,"y":162,"w":154,"h":163},"80003":{"x":439,"y":0,"w":181,"h":182},"80004":{"x":154,"y":163,"w":159,"h":183},"80005":{"x":313,"y":163,"w":116,"h":165},"80006":{"x":0,"y":325,"w":116,"h":171}},"mc":{"70109_a_8":{"frameRate":15,"frames":[{"y":-133,"res":"80000","x":-118},{"y":-133,"res":"80001","x":-99},{"y":-140,"res":"80002","x":-74},{"y":-146,"res":"80003","x":-101},{"y":-159,"res":"80004","x":-88},{"y":-155,"res":"80005","x":-62},{"y":-155,"res":"80006","x":-57}]}}}